Workbook

Sheet Cover Sheet
B3: Electric car company case study - solution
B7: This workbook contains a solution for the electric car company case study. - Sheet 1 "Input data" contains the input data for this case study - Sheet 2 "Constants-assumptions" contains several constants and assumptions used for the analysis - Sheet 3 "Calculations" contain the calculations A synthesis and recommendations would be added later

Sheet input data
A1: This sheet contains input data for the electric car company case study
B3: Data item | C3: status quo | D3: 2020 | E3: 2021 | F3: 2022
B4: Fixed costs (e.g., general and administration) | D4: 10000000 | E4: 11000000 | F4: 12000000
B5: Research and development costs | D5: 7500000 | E5: 5000000 | F5: 4000000
B6: Production cost per vehicle | D6: 35000 | E6: 33500 | F6: 32000
B7: Number of charger locations | C7: 750
B8: Cars sold | C8: 5000

Sheet Calculations
A1: This sheet is used to calculate profit after taxes of the electric car company
B3: Structure | C3: Data item | D3: 2020 | E3: 2021 | F3: 2022 | G3: Comment
B4: Basic calculations | C4: Number of charger locations | D4: ='input data'!C7+'Constants-assumptions'!C10 -> 850 | E4: =D4+'Constants-assumptions'!C11 -> 930 | F4: =E4+'Constants-assumptions'!C12 -> 1005
B5: Revenue calculation | C5: Price per vehicle | D5: ='Constants-assumptions'!$C$6 -> 43000 | E5: ='Constants-assumptions'!$C$6 -> 43000 | F5: ='Constants-assumptions'!$C$6 -> 43000 | G5: Vehicle price stays constant over the years
C6: Gas price effect | D6: =IF('Constants-assumptions'!C7="down",-5%,IF('Constants-assumptions'!C7="same",0%,10%)) -> -0.05 | E6: =IF('Constants-assumptions'!C8="down",-5%,IF('Constants-assumptions'!C8="same",0%,10%)) -> 0 | F6: =IF('Constants-assumptions'!C9="down",-5%,IF('Constants-assumptions'!C9="same",0%,10%)) -> 0.1 | G6: If the gas price goes up, sales go up by 10%. If the gas price stays the same, sales do not change. If the gas price goes down, sales go down by 5%.
C7: New charger location effect | D7: =IF('Constants-assumptions'!C10>=100,10%,0%) -> 0.1 | E7: =IF('Constants-assumptions'!C11>=100,10%,0) -> 0 | F7: =IF('Constants-assumptions'!C12>=100,10%,0%) -> 0 | G7: If the company introduces more than 99 new charger locations (>=100) in the year, sales go up by 10% for marketing reasons
C8: Charger location network effect | D8: =IF(D$4>=1000,10%,0) -> 0 | E8: =IF(E$4>=1000,10%,0) -> 0 | F8: =IF(F$4>=1000,10%,0) -> 0.1 | G8: If the company has overall more than 999 charger locations (>=1000), sales go up by 10% for marketing reasons
C9: Change in units sold | D9: =SUM(D$6:D$8) -> 0.05 | E9: =SUM(E$6:E$8) -> 0 | F9: =SUM(F$6:F$8) -> 0.2 | G9: Change in units sold is the sum of new charger location effect, charger location network effect, and gas price effect
C10: Vehicles sold | D10: ='input data'!C8*(1+Calculations!D$9) -> 5250 | E10: =D$10*(1+E$9) | F10: =E$10*(1+F$9) | G10: Number of vehicles sold is dependent on the vehicles sold in the previous year and the change in units sold
C11: Revenue | D11: =D$10*D$5 -> 225750000 | E11: =E$10*E$5 -> 225750000 | F11: =F$10*F$5 -> 270900000
B12: Cost calculation | C12: Fixed costs (e.g., general and administration) | D12: ='input data'!D4 -> 10000000 | E12: ='input data'!E4 -> 11000000 | F12: ='input data'!F4 -> 12000000
C13: Research and development costs | D13: ='input data'!D5 -> 7500000 | E13: ='input data'!E5 -> 5000000 | F13: ='input data'!F5 -> 4000000
C14: Production cost | D14: =D$10*'input data'!D$6 -> 183750000 | E14: =E$10*'input data'!E$6 -> 175875000 | F14: =F$10*'input data'!F$6 -> 201600000
C15: Charger location costs | D15: =D$4*'Constants-assumptions'!$C$5 -> 35700000 | E15: =E$4*'Constants-assumptions'!$C$5 -> 39060000 | F15: =F$4*'Constants-assumptions'!$C$5 -> 42210000
C16: Costs | D16: =SUM(D$12:D$15) -> 236950000 | E16: =SUM(E$12:E$15) -> 230935000 | F16: =SUM(F$12:F$15) -> 259810000
B17: Profit | C17: Profit before taxes | D17: =D$11-D$16 -> -11200000 | E17: =E$11-E$16 -> -5185000 | F17: =F$11-F$16 -> 11090000
C18: Profit after taxes | D18: =D$17*(1-'Constants-assumptions'!$C$4) -> -8960000 | E18: =E$17*(1-'Constants-assumptions'!$C$4) -> -4148000 | F18: =F$17*(1-'Constants-assumptions'!$C$4) -> 8872000 | G18: Tax return can be claimed in years of loss (assume profit after taxes is always profit x tax rate, even if profit is negative)

Sheet Constants-assumptions
A1: This sheet contains constants and assumptions for the electric car company case study
B3: Constant/assumption | C3: Value | D3: Comments
B4: Tax rate | C4: 0.2
B5: Costs of operating a charger station | C5: 42000 | D5: Yearly costs to operate a charger station
B6: Price per vehicle | C6: 43000
B7: Gas price change in 2020 | C7: down | D7: Fuel price change in 2020 (used for gas price effect of sales)
B8: Gas price change in 2021 | C8: same | D8: Fuel price change in 2021 (used for gas price effect of sales)
B9: Gas price change in 2022 | C9: up | D9: Fuel price change in 2022 (used for gas price effect of sales)
B10: New charger locations in 2020 | C10: 100 | D10: Number of new charger locations in 2020 (used for charger location effects of sales)
B11: New charger locations in 2021 | C11: 80 | D11: Number of new charger locations in 2021 (used for charger location effects of sales)
B12: New charger locations in 2022 | C12: 75 | D12: Number of new charger locations in 2022 (used for charger location effects of sales)
