Workbook

Sheet Cover Sheet
B3: New York Taxi Driver Case Study - Data
B7: This workbook contains data for the New York Taxi Driver Case Study. Sheet 1 "1 - input data" contains data for both scenario.

Sheet 1 - input data
A1: Data sheet for both scenarios
B3: Variable | C3: Value | D3: Comment
B4: Time in queue, in hours | C4: 2 | D4: Average time to wait at the airport (no differentiation of time of day in this case study) - Stay scenario
B5: Fare, 1st mile, in USD | C5: 4 | D5: Includes flag drop charge
B6: Fare, additional mile, in USD | C6: 2
B7: Tips, in % of fare | C7: 15 | D7: Passenger pays 15% tip on top of the fare; tips are rounded to the nearest Dollar
B8: Toll, in USD | C8: 3 | D8: There is a $3 tunnel/bridge between LaGuardia and Manhattan
B9: Passenger share of toll, in % | C9: 100 | D9: Passenger pays the toll (if one is in the cab)
B10: Distance LaGuardia-Manhattan, in Miles | C10: 12 | D10: Each trip from LaGuardia to Manhattan has an average length of 12 miles (we neglect shorter/longer trips), assume this is all highway
B11: Average inner-city tour distance, in Miles | C11: 2 | D11: Each trip in Manhattan has an average length of 2 miles (we neglect shorter/longer trips) - Leave scenario
B12: Car ownership costs, in % of fare | C12: 50 | D12: Car is owned by a cab company. Driver gives 50% of fees to cab company
B13: Fuel consumption, city, in miles per gallon | C13: 12 | D13: Fuel consumption in the city
B14: Fuel consumption, highway, in miles per gallon | C14: 24 | D14: Fuel consumption on highways
B15: Fuel consumption, waiting at airport | C15: 0
B16: Fuel price, in USD per gallon | C16: 2
B17: Average inner-city driving speed, in Miles per hour | C17: 12 | D17: Average driving speed looking for passengers/having passengers in Manhattan - Leave scenario
B18: Average high-way speed, in Miles per hour | C18: 36 | D18: Average driving speed driving on the highway from the Airport to Manhattan
B19: Average search time between trip, in minutes | C19: 10 | D19: Driving In the city results in one tour after (on average) 10 minutes of wait time - Leave scenario

Sheet Stay scenario
A1: Calculation sheet for Stay scenario
B4: Variable | C4: Value | D4: Comment
B5: Revenue | C5: ='1 - input data'!C5+('1 - input data'!C10-1)*'1 - input data'!C6 -> 26 | D5: Distance from airport to city multiply with fare
B6: Tip | C6: =ROUND(C5*'1 - input data'!C7/100,0) -> 4
B7: Fuel consumption in highway | C7: ='1 - input data'!C10/'1 - input data'!C14*'1 - input data'!C16 -> 1
B8: Money giving to company | C8: ='Stay scenario'!C5*'1 - input data'!C12/100 -> 13
B9: Toll | C9: =(1-'1 - input data'!C9/100)*'1 - input data'!C8 | D9: passenger is paying the toll
B10: Total profit | C10: =C5+C6-C7-C8-C9
B11: Total time | C11: ='1 - input data'!C4+'1 - input data'!C10/'1 - input data'!C18 -> 2.3333333

Sheet leave scenario
A1: Calculation sheet for Leave scenario
B4: Variable | C4: Value | D4: Comment
B5: transfer time | C5: ='1 - input data'!C10/'1 - input data'!C18 -> 0.33333333
B6: transfer fuel cost | C6: ='1 - input data'!C10/'1 - input data'!C14*'1 - input data'!C16 -> 1
B7: Toll paid by driver | C7: ='1 - input data'!C8 -> 3
B8: search time for trip, in hours | C8: ='1 - input data'!C19/60 -> 0.16666667
B9: time needed per trip, in hours | C9: ='leave scenario'!C8+'1 - input data'!C11/'1 - input data'!C17 -> 0.33333333
B10: miles covered between search time | C10: ='leave scenario'!C8*'1 - input data'!C17 -> 2
B11: total fuel consumption cost per trip | C11: =(C10+'1 - input data'!C11)/'1 - input data'!C13*'1 - input data'!C16 -> 0.66666667
B12: total possible trip | C12: =('Stay scenario'!C11-'leave scenario'!C5)/'leave scenario'!C9 -> 6
B13: Revenue per trip | C13: ='1 - input data'!C5+('1 - input data'!C11-1)*'1 - input data'!C6
B14: Tip | C14: =ROUND(C13*'1 - input data'!C7/100,0) -> 1
B15: Car ownership cost | C15: =C13*'1 - input data'!C12/100 -> 3
B16: Total profit per trip | C16: =C13+C14-C15-C11 -> 3.3333333
B17: Total profit | C17: =C12*C16-C7-C6

Sheet result
A3: Results for the New York Taxi Driver case study
D6: Stay scenario | E6: Leave scenario
C7: Total time, in hours | D7: ='Stay scenario'!C11 -> 2.3333333 | E7: =D7 -> 2.3333333
C8: Total profit | D8: ='Stay scenario'!C10 | E8: ='leave scenario'!C17 -> 16
